income_predict/FlowIncomePredict.py
income_predict/__init__.py
FlowIncomePredict-0.0.2.dist-info/LICENCE
FlowIncomePredict-0.0.2.dist-info/METADATA
FlowIncomePredict-0.0.2.dist-info/WHEEL
FlowIncomePredict-0.0.2.dist-info/top_level.txt
FlowIncomePredict-0.0.2.dist-info/RECORD
